binip/__init__.py
binip/classes.py
binip/functions.py
binip-1.0.2.dist-info/METADATA
binip-1.0.2.dist-info/WHEEL
binip-1.0.2.dist-info/licenses/LICENSE
binip-1.0.2.dist-info/RECORD
