Metadata-Version: 2.3
Name: binip
Version: 1.0.2
Summary: A package for facilitating various IP and subnet operations.
Project-URL: Homepage, https://github.com/loicjamesmckeever/binip
Project-URL: Issues, https://github.com/loicjamesmckeever/binip/issues
Author-email: Loïc James McKeever <loicjamesmckeever@gmail.com>
License: Copyright (c) 2018 The Python Packaging Authority
License-File: LICENSE
Keywords: IP,network,subnet
Classifier: License :: OSI Approved :: MIT License
Classifier: Operating System :: OS Independent
Classifier: Programming Language :: Python :: 3
Requires-Python: >=3.7
